LICENSE
README.md
setup.cfg
setup.py
PyInformix.egg-info/PKG-INFO
PyInformix.egg-info/SOURCES.txt
PyInformix.egg-info/dependency_links.txt
PyInformix.egg-info/entry_points.txt
PyInformix.egg-info/not-zip-safe
PyInformix.egg-info/requires.txt
PyInformix.egg-info/top_level.txt
pyinformix/__init__.py
pyinformix/ibm_db.py
pyinformix/ifx_jdbc.py
pyinformix/requirements.py