Metadata-Version: 2.1
Name: PyInformix
Version: 0.2.0
Summary: Experimental SQLAlchemy dialect for IBM Informix
Home-page: https://github.com/homedepot/pyinformix
Author: Mike Phillipson
Author-email: MICHAEL_PHILLIPSON1@homedepot.com
License: Apache 2.0
Platform: UNKNOWN
License-File: LICENSE
